crop_scanned_photos/__init__.py
crop_scanned_photos/main.py
crop_scanned_photos-0.1.2.dist-info/LICENSE
crop_scanned_photos-0.1.2.dist-info/METADATA
crop_scanned_photos-0.1.2.dist-info/WHEEL
crop_scanned_photos-0.1.2.dist-info/RECORD
