Metadata-Version: 2.3
Name: crop-scanned-photos
Version: 0.1.2
Summary: A tool to detect and crop multiple photos from scanned images
Author: Pedro Soares
Author-email: pedrofigueiredoc@gmail.com
Requires-Python: >=3.8.1,<4.0
Classifier: Programming Language :: Python :: 3
Classifier: Programming Language :: Python :: 3.9
Classifier: Programming Language :: Python :: 3.10
Classifier: Programming Language :: Python :: 3.11
Classifier: Programming Language :: Python :: 3.12
Classifier: Programming Language :: Python :: 3.13
Requires-Dist: Pillow (>=10.1.0,<11.0.0)
Requires-Dist: opencv-python (>=4.8.1.78,<5.0.0.0)
Project-URL: Repository, https://github.com/hspedro/crop-scanned-photos
